LICENSE
MANIFEST.in
README.md
setup.cfg
setup.py
dvci/__init__.py
dvci/app_version.py
dvci/arguments.py
dvci/commands.py
dvci/docums_plugin.py
dvci/docums_utils.py
dvci/driver.py
dvci/git_utils.py
dvci/server.py
dvci/versions.py
dvci.egg-info/PKG-INFO
dvci.egg-info/SOURCES.txt
dvci.egg-info/dependency_links.txt
dvci.egg-info/entry_points.txt
dvci.egg-info/not-zip-safe
dvci.egg-info/requires.txt
dvci.egg-info/top_level.txt
dvci/templates/__init__.py
dvci/templates/redirect.html
dvci/themes/__init__.py
dvci/themes/docums/__init__.py
dvci/themes/docums/css/version-select.css
dvci/themes/docums/js/version-select.js
dvci/themes/readthedocs/__init__.py
dvci/themes/readthedocs/css/version-select.css
dvci/themes/readthedocs/js/version-select.js