Metadata-Version: 2.1
Name: dvci
Version: 1.2.0.dev0
Summary: Manage multiple versions of your Docums-powered documentation
Home-page: https://github.com/khanhduy1407/dvci
Author: NKDuy
Author-email: kn145660@gmail.com
License: BSD
Keywords: docums multiple versions
Platform: UNKNOWN
Classifier: Development Status :: 5 - Production/Stable
Classifier: Intended Audience :: Developers
Classifier: Topic :: Documentation
Classifier: License :: OSI Approved :: BSD License
Classifier: Programming Language :: Python :: 3
Classifier: Programming Language :: Python :: 3.6
Classifier: Programming Language :: Python :: 3.7
Classifier: Programming Language :: Python :: 3.8
Classifier: Programming Language :: Python :: 3.9
Classifier: Programming Language :: Python :: 3.10
Provides-Extra: dev
Provides-Extra: test
